migrations/0001_initial.py
migrations/0002_newslettercampaign_newsletterrecipient.py
migrations/0003_alter_newslettercampaign_options_and_more.py
migrations/0004_alter_newslettercampaign_options_and_more.py
migrations/0005_alter_sendernetsettings_api_key.py
migrations/0006_alter_sendernetsettings_api_key.py
migrations/__init__.py
sender_net-0.1.0.dist-info/LICENSE
sender_net-0.1.0.dist-info/METADATA
sender_net-0.1.0.dist-info/WHEEL
sender_net-0.1.0.dist-info/top_level.txt
sender_net-0.1.0.dist-info/RECORD
